config.py
leetagent_launcher.py
main.py
agents/__init__.py
agents/decision_agent.py
cli/__init__.py
cli/main_cli.py
cli/typer_cli.py
core/__init__.py
core/logger.py
core/telegram_client.py
core/utils.py
leetagent/__init__.py
leetagent/__main__.py
leetagent/post_install.py
leetagent/setup_path.py
leetagent-1.0.6.dist-info/licenses/LICENSE
modules/__init__.py
modules/ai_generator.py
modules/auth.py
modules/browser_controller.py
modules/formatter.py
modules/notifier.py
modules/notifier_backup.py
modules/scraper.py
utils/IMPORT_GUIDE.py
utils/README.md
utils/__init__.py
utils/example_usage.py
utils/text_helpers.py
leetagent-1.0.6.dist-info/METADATA
leetagent-1.0.6.dist-info/WHEEL
leetagent-1.0.6.dist-info/entry_points.txt
leetagent-1.0.6.dist-info/top_level.txt
leetagent-1.0.6.dist-info/RECORD
