Metadata-Version: 2.4
Name: leetagent
Version: 1.0.6
Summary: LeetAgentAutoSat — The Smart LeetCode AI Automation Tool
Home-page: https://github.com/satyamyadav/leetagent
Author: Satyam Yadav
Author-email: Satyam Yadav <satyamyadavaiml@gmail.com>
Maintainer-email: Satyam Yadav <satyamyadavaiml@gmail.com>
License-Expression: MIT
Project-URL: Homepage, https://github.com/satyamyadav/leetagent
Project-URL: Documentation, https://github.com/satyamyadav/leetagent#readme
Project-URL: Repository, https://github.com/satyamyadav/leetagent
Project-URL: Bug Tracker, https://github.com/satyamyadav/leetagent/issues
Keywords: leetcode,automation,ai,gemini,selenium,coding,interview-prep
Classifier: Development Status :: 4 - Beta
Classifier: Intended Audience :: Developers
Classifier: Topic :: Software Development :: Code Generators
Classifier: Topic :: Education
Classifier: Programming Language :: Python :: 3
Classifier: Programming Language :: Python :: 3.10
Classifier: Programming Language :: Python :: 3.11
Classifier: Programming Language :: Python :: 3.12
Requires-Python: >=3.10
License-File: LICENSE
Requires-Dist: google-generativeai>=0.3.0
Requires-Dist: selenium>=4.15.0
Requires-Dist: webdriver-manager>=4.0.1
Requires-Dist: requests>=2.31.0
Requires-Dist: httpx>=0.25.0
Requires-Dist: python-dotenv>=1.0.0
Requires-Dist: keyring>=24.0.0
Requires-Dist: rich>=13.7.0
Requires-Dist: typer>=0.9.0
Requires-Dist: click>=8.1.0
Requires-Dist: aiohttp>=3.9.0
Provides-Extra: dev
Requires-Dist: pytest>=7.4.0; extra == "dev"
Requires-Dist: pytest-cov>=4.1.0; extra == "dev"
Requires-Dist: pytest-asyncio>=0.21.0; extra == "dev"
Requires-Dist: black>=23.0.0; extra == "dev"
Requires-Dist: flake8>=6.1.0; extra == "dev"
Requires-Dist: mypy>=1.7.0; extra == "dev"
Provides-Extra: ai
Requires-Dist: langchain>=0.1.0; extra == "ai"
Requires-Dist: langchain-openai>=0.0.2; extra == "ai"
Requires-Dist: chromadb>=0.4.0; extra == "ai"
Requires-Dist: openai>=1.0.0; extra == "ai"
Dynamic: author
Dynamic: home-page
Dynamic: license-file
Dynamic: requires-python
